{
    "paths" : [
        "MainMethods",
        "MainInterfaces",
        "MainTraits",
        "Domain",
        "DomainTraits",
        "Connectors",
        "DomainInterfaces",
        "GrendelRequests",
        "GrendelRoutes",
        "GrendelPager",
        "GrendelDb",
        "GrendelDatas",
        "GrendelTpl",
        "User",
        "Models"
    ],
    "MainMethods" : "core/methods/",
    "MainInterfaces" : "core/Interfaces/",
    "MainTraits" : "core/Traits/",
    "Domain" : "domain/",
    "DomainTraits" : "domain/Traits/",
    "Connectors" : "domain/Connectors/",
    "DomainInterfaces" : "domain/Interfaces/",
    "GrendelRequests" : "libs/GrendelRequests/",
    "GrendelRoutes" : "libs/GrendelRoutes/",
    "GrendelPager" : "libs/GrendelPager/",
    "GrendelDb" : "GrendelDb/",
    "GrendelDatas" : "libs/GrendelDatas/",
    "GrendelTpl" : "libs/GrendelTpl/",
    "User" : "devs/",
    "Models" : "devs/Models/"
}
